{
  "packages" : [
    {
      "path" : "trust/package-list.json",
      "package-id" : "smart.who.int.trust",
      "title" : "Trust",
      "canonical" : "http://smart.who.int/trust",
      "category" : "base",
      "ci-build" : "http://worldhealthorganization.github.io/smart-trust",
      "version-count" : 1,
      "latest" : {
        "version" : "1.0.0",
        "date" : "2024-01-29",
        "path" : "http://smart.who.int/trust/1.0.0"
      },
      "milestone" : {
        "version" : "1.0.0",
        "date" : "2024-01-29",
        "path" : "http://smart.who.int/trust/1.0.0"
      }
    }
  ]
}
