{
  "resourceType" : "Bundle",
  "id" : "23864404-2b4f-4bbc-885a-96b95ce79748",
  "meta" : {
    "lastUpdated" : "2025-05-07T08:18:56.104+00:00"
  },
  "type" : "collection",
  "entry" : [{
    "fullUrl" : "http://smart.who.int/trust/ValueSet/Actors",
    "resource" : {
      "resourceType" : "ValueSet",
      "text" : {
        "status" : "generated",
        "div" : "<div xmlns=\"http://www.w3.org/1999/xhtml\"><p class=\"res-header-id\"><b>ValueSet </b></p><p style=\"border: black 1px dotted; background-color: #EEEEEE; padding: 8px; margin-bottom: 8px\">Expansion performed internally based on <a href=\"CodeSystem-Actors.html\">codesystem WHO GDHCN Trust Actors CodeSystem v1.1.6 (CodeSystem)</a></p><p>This value set contains 5 concepts</p><table class=\"codes\"><tr><td style=\"white-space:nowrap\"><b>Code</b></td><td><b>System</b></td><td><b>Display (en-US)</b></td><td><b>Definition</b></td></tr><tr><td style=\"white-space:nowrap\"><a name=\"x-http://smart.who.int/trust/CodeSystem/Actors-credential-holder\"> </a>\u00a0\u00a0<a href=\"CodeSystem-Actors.html#Actors-credential-holder\">credential-holder</a></td><td>http://smart.who.int/trust/CodeSystem/Actors</td><td>Holder of a Credential</td><td><div/></td></tr><tr><td style=\"white-space:nowrap\"><a name=\"x-http://smart.who.int/trust/CodeSystem/Actors-credential-issuer\"> </a>\u00a0\u00a0<a href=\"CodeSystem-Actors.html#Actors-credential-issuer\">credential-issuer</a></td><td>http://smart.who.int/trust/CodeSystem/Actors</td><td>Issuer of a Credential</td><td><div/></td></tr><tr><td style=\"white-space:nowrap\"><a name=\"x-http://smart.who.int/trust/CodeSystem/Actors-gdhcn\"> </a>\u00a0\u00a0<a href=\"CodeSystem-Actors.html#Actors-gdhcn\">gdhcn</a></td><td>http://smart.who.int/trust/CodeSystem/Actors</td><td>GDHCN</td><td><div><p>Global Digital Health Certification Network (GDHCN)</p>\n</div></td></tr><tr><td style=\"white-space:nowrap\"><a name=\"x-http://smart.who.int/trust/CodeSystem/Actors-TNG\"> </a>\u00a0\u00a0<a href=\"CodeSystem-Actors.html#Actors-TNG\">TNG</a></td><td>http://smart.who.int/trust/CodeSystem/Actors</td><td>TNG</td><td><div><p>Trust Network Gateway</p>\n</div></td></tr><tr><td style=\"white-space:nowrap\"><a name=\"x-http://smart.who.int/trust/CodeSystem/Actors-TNP\"> </a>\u00a0\u00a0<a href=\"CodeSystem-Actors.html#Actors-TNP\">TNP</a></td><td>http://smart.who.int/trust/CodeSystem/Actors</td><td>TNP</td><td><div><p>Trust Network Participant</p>\n</div></td></tr></table></div>"
      },
      "url" : "http://smart.who.int/trust/ValueSet/Actors",
      "version" : "1.1.6",
      "name" : "Actors",
      "title" : "WHO GDHCN Actor ValueSet of actor codes",
      "status" : "active",
      "experimental" : true,
      "date" : "2025-05-07T08:17:04+00:00",
      "jurisdiction" : [{
        "coding" : [{
          "system" : "http://unstats.un.org/unsd/methods/m49/m49.htm",
          "code" : "001"
        }]
      }],
      "expansion" : {
        "identifier" : "urn:uuid:1e621bef-7148-4907-b2e5-ff59f88b638d",
        "timestamp" : "2025-05-07T08:21:17+00:00",
        "total" : 5,
        "offset" : 0,
        "parameter" : [{
          "name" : "displayLanguage",
          "valueCode" : "en-US"
        },
        {
          "name" : "count",
          "valueInteger" : 1000
        },
        {
          "name" : "offset",
          "valueInteger" : 0
        },
        {
          "name" : "excludeNested",
          "valueBoolean" : false
        },
        {
          "name" : "used-codesystem",
          "valueUri" : "http://smart.who.int/trust/CodeSystem/Actors|1.1.6"
        }],
        "contains" : [{
          "system" : "http://smart.who.int/trust/CodeSystem/Actors",
          "code" : "credential-holder",
          "display" : "Holder of a Credential"
        },
        {
          "system" : "http://smart.who.int/trust/CodeSystem/Actors",
          "code" : "credential-issuer",
          "display" : "Issuer of a Credential"
        },
        {
          "system" : "http://smart.who.int/trust/CodeSystem/Actors",
          "code" : "gdhcn",
          "display" : "GDHCN"
        },
        {
          "system" : "http://smart.who.int/trust/CodeSystem/Actors",
          "code" : "TNG",
          "display" : "TNG"
        },
        {
          "system" : "http://smart.who.int/trust/CodeSystem/Actors",
          "code" : "TNP",
          "display" : "TNP"
        }]
      }
    }
  },
  {
    "fullUrl" : "http://smart.who.int/trust/ValueSet/ConnectionTypes",
    "resource" : {
      "resourceType" : "ValueSet",
      "text" : {
        "status" : "generated",
        "div" : "<div xmlns=\"http://www.w3.org/1999/xhtml\"><p class=\"res-header-id\"><b>ValueSet </b></p><p style=\"border: black 1px dotted; background-color: #EEEEEE; padding: 8px; margin-bottom: 8px\">Expansion performed internally based on <a href=\"CodeSystem-ConnectionTypes.html\">codesystem WHO GDHCN Connection Types v1.1.6 (CodeSystem)</a></p><p>This value set contains 2 concepts</p><table class=\"codes\"><tr><td style=\"white-space:nowrap\"><b>Code</b></td><td><b>System</b></td><td><b>Display (en-US)</b></td><td><b>Definition</b></td></tr><tr><td style=\"white-space:nowrap\"><a name=\"x-http://smart.who.int/trust/CodeSystem/ConnectionTypes-http-get\"> </a>\u00a0\u00a0<a href=\"CodeSystem-ConnectionTypes.html#ConnectionTypes-http-get\">http-get</a></td><td>http://smart.who.int/trust/CodeSystem/ConnectionTypes</td><td>http-get</td><td><div><p>http(s) GET request</p>\n</div></td></tr><tr><td style=\"white-space:nowrap\"><a name=\"x-http://smart.who.int/trust/CodeSystem/ConnectionTypes-mtls\"> </a>\u00a0\u00a0<a href=\"CodeSystem-ConnectionTypes.html#ConnectionTypes-mtls\">mtls</a></td><td>http://smart.who.int/trust/CodeSystem/ConnectionTypes</td><td>mTLS</td><td><div><p>mutual TLS (mTLS)</p>\n</div></td></tr></table></div>"
      },
      "url" : "http://smart.who.int/trust/ValueSet/ConnectionTypes",
      "version" : "1.1.6",
      "name" : "ConnectionTypes",
      "title" : "WHO GDHCN Connection Types",
      "status" : "active",
      "experimental" : true,
      "date" : "2025-05-07T08:17:04+00:00",
      "jurisdiction" : [{
        "coding" : [{
          "system" : "http://unstats.un.org/unsd/methods/m49/m49.htm",
          "code" : "001"
        }]
      }],
      "expansion" : {
        "identifier" : "urn:uuid:ba794178-3c62-47e7-97c3-6583cfa771ed",
        "timestamp" : "2025-05-07T08:21:17+00:00",
        "total" : 2,
        "offset" : 0,
        "parameter" : [{
          "name" : "displayLanguage",
          "valueCode" : "en-US"
        },
        {
          "name" : "count",
          "valueInteger" : 1000
        },
        {
          "name" : "offset",
          "valueInteger" : 0
        },
        {
          "name" : "excludeNested",
          "valueBoolean" : false
        },
        {
          "name" : "used-codesystem",
          "valueUri" : "http://smart.who.int/trust/CodeSystem/ConnectionTypes|1.1.6"
        }],
        "contains" : [{
          "system" : "http://smart.who.int/trust/CodeSystem/ConnectionTypes",
          "code" : "http-get",
          "display" : "http-get"
        },
        {
          "system" : "http://smart.who.int/trust/CodeSystem/ConnectionTypes",
          "code" : "mtls",
          "display" : "mTLS"
        }]
      }
    }
  },
  {
    "fullUrl" : "http://smart.who.int/trust/ValueSet/Domains",
    "resource" : {
      "resourceType" : "ValueSet",
      "text" : {
        "status" : "generated",
        "div" : "<div xmlns=\"http://www.w3.org/1999/xhtml\"><p class=\"res-header-id\"><b>ValueSet </b></p><p style=\"border: black 1px dotted; background-color: #EEEEEE; padding: 8px; margin-bottom: 8px\">Expansion performed internally based on <a href=\"CodeSystem-Domains.html\">codesystem WHO GDHCN Trust Domains v1.1.6 (CodeSystem)</a></p><p>This value set contains 4 concepts</p><table class=\"codes\"><tr><td style=\"white-space:nowrap\"><b>Code</b></td><td><b>System</b></td><td><b>Display (en-US)</b></td><td><b>Definition</b></td></tr><tr><td style=\"white-space:nowrap\"><a name=\"x-http://smart.who.int/trust/CodeSystem/Domains-DDCC\"> </a>\u00a0\u00a0<a href=\"CodeSystem-Domains.html#Domains-DDCC\">DDCC</a></td><td>http://smart.who.int/trust/CodeSystem/Domains</td><td>DDCC</td><td><div><p>The Digital Documentation for COVID-19 Certificates (DDCC) is defined by the SMART Implementation Guide at http://smart.who.int/ddcc</p>\n</div></td></tr><tr><td style=\"white-space:nowrap\"><a name=\"x-http://smart.who.int/trust/CodeSystem/Domains-IPS-PILGRIMAGE\"> </a>\u00a0\u00a0<a href=\"CodeSystem-Domains.html#Domains-IPS-PILGRIMAGE\">IPS-PILGRIMAGE</a></td><td>http://smart.who.int/trust/CodeSystem/Domains</td><td>IPS for Pilgrimage</td><td><div><p>The IPS for Pilgrimage is defined by the SMART Implementation Guide at http://smart.who.int/ips-pilgrimage</p>\n</div></td></tr><tr><td style=\"white-space:nowrap\"><a name=\"x-http://smart.who.int/trust/CodeSystem/Domains-PH4H\"> </a>\u00a0\u00a0<a href=\"CodeSystem-Domains.html#Domains-PH4H\">PH4H</a></td><td>http://smart.who.int/trust/CodeSystem/Domains</td><td>Pan-American Highway for Digital Health (PH4H)</td><td><div><p>The Pan-American Highway for Digital Health (PH4H) is defined by\u00a0SMART Implementation Guide at https://worldhealthorganization.github.io/smart-ph4h/</p>\n</div></td></tr><tr><td style=\"white-space:nowrap\"><a name=\"x-http://smart.who.int/trust/CodeSystem/Domains-ICVP\"> </a>\u00a0\u00a0<a href=\"CodeSystem-Domains.html#Domains-ICVP\">ICVP</a></td><td>http://smart.who.int/trust/CodeSystem/Domains</td><td>International Certificate of Vaccination of Prophylaxsis (ICVP)</td><td><div><p>The International Certificate of Vaccination of Prophylaxsis (ICVP) is defined by\u00a0SMART Implementation Guide at https://worldhealthorganization.github.io/smart-icvp/</p>\n</div></td></tr></table></div>"
      },
      "url" : "http://smart.who.int/trust/ValueSet/Domains",
      "version" : "1.1.6",
      "name" : "Domains",
      "title" : "WHO GDHCN Trust Domains",
      "status" : "draft",
      "experimental" : false,
      "date" : "2025-05-07T08:17:04+00:00",
      "jurisdiction" : [{
        "coding" : [{
          "system" : "http://unstats.un.org/unsd/methods/m49/m49.htm",
          "code" : "001"
        }]
      }],
      "expansion" : {
        "identifier" : "urn:uuid:f9ad8110-21dc-4964-8b78-c1dac76febe9",
        "timestamp" : "2025-05-07T08:21:18+00:00",
        "total" : 4,
        "offset" : 0,
        "parameter" : [{
          "name" : "displayLanguage",
          "valueCode" : "en-US"
        },
        {
          "name" : "count",
          "valueInteger" : 1000
        },
        {
          "name" : "offset",
          "valueInteger" : 0
        },
        {
          "name" : "excludeNested",
          "valueBoolean" : false
        },
        {
          "name" : "used-codesystem",
          "valueUri" : "http://smart.who.int/trust/CodeSystem/Domains|1.1.6"
        }],
        "contains" : [{
          "system" : "http://smart.who.int/trust/CodeSystem/Domains",
          "code" : "DDCC",
          "display" : "DDCC"
        },
        {
          "system" : "http://smart.who.int/trust/CodeSystem/Domains",
          "code" : "IPS-PILGRIMAGE",
          "display" : "IPS for Pilgrimage"
        },
        {
          "system" : "http://smart.who.int/trust/CodeSystem/Domains",
          "code" : "PH4H",
          "display" : "Pan-American Highway for Digital Health (PH4H)"
        },
        {
          "system" : "http://smart.who.int/trust/CodeSystem/Domains",
          "code" : "ICVP",
          "display" : "International Certificate of Vaccination of Prophylaxsis (ICVP)"
        }]
      }
    }
  },
  {
    "fullUrl" : "http://smart.who.int/trust/ValueSet/KeyUsage",
    "resource" : {
      "resourceType" : "ValueSet",
      "text" : {
        "status" : "generated",
        "div" : "<div xmlns=\"http://www.w3.org/1999/xhtml\"><p class=\"res-header-id\"><b>ValueSet </b></p><p style=\"border: black 1px dotted; background-color: #EEEEEE; padding: 8px; margin-bottom: 8px\">Expansion performed internally based on <a href=\"CodeSystem-KeyUsage.html\">codesystem WHO GDHCN Key Usage CodeSystem v1.1.6 (CodeSystem)</a></p><p>This value set contains 4 concepts</p><table class=\"codes\"><tr><td style=\"white-space:nowrap\"><b>Code</b></td><td><b>System</b></td><td><b>Display (en-US)</b></td><td><b>Definition</b></td></tr><tr><td style=\"white-space:nowrap\"><a name=\"x-http://smart.who.int/trust/CodeSystem/KeyUsage-SCA\"> </a>\u00a0\u00a0<a href=\"CodeSystem-KeyUsage.html#KeyUsage-SCA\">SCA</a></td><td>http://smart.who.int/trust/CodeSystem/KeyUsage</td><td>Signing Certificate Authority</td><td><div><p>A certificate which acts a trust anchor in the verification of the certificate chain for the DSCs issued by a Trust Network participant</p>\n</div></td></tr><tr><td style=\"white-space:nowrap\"><a name=\"x-http://smart.who.int/trust/CodeSystem/KeyUsage-DSC\"> </a>\u00a0\u00a0<a href=\"CodeSystem-KeyUsage.html#KeyUsage-DSC\">DSC</a></td><td>http://smart.who.int/trust/CodeSystem/KeyUsage</td><td>Document Signing Certificate</td><td><div><p>A certificate which may be used to verify a digital signature within a Verfifiable Digital Health Certificate</p>\n</div></td></tr><tr><td style=\"white-space:nowrap\"><a name=\"x-http://smart.who.int/trust/CodeSystem/KeyUsage-UP\"> </a>\u00a0\u00a0<a href=\"CodeSystem-KeyUsage.html#KeyUsage-UP\">UP</a></td><td>http://smart.who.int/trust/CodeSystem/KeyUsage</td><td>Upload</td><td><div><p>Used to verify digital signature of cryptographically signed content uploaded to services within the Global Digital Health Certification Network, in particular the Trust Network Gateway</p>\n</div></td></tr><tr><td style=\"white-space:nowrap\"><a name=\"x-http://smart.who.int/trust/CodeSystem/KeyUsage-TLS\"> </a>\u00a0\u00a0<a href=\"CodeSystem-KeyUsage.html#KeyUsage-TLS\">TLS</a></td><td>http://smart.who.int/trust/CodeSystem/KeyUsage</td><td>TLS</td><td><div><p>Used for establishing (m)TLS connections with systems, in particular between the Trust Network Gateway and backend systems of a Trust Network Participant</p>\n</div></td></tr></table></div>"
      },
      "url" : "http://smart.who.int/trust/ValueSet/KeyUsage",
      "version" : "1.1.6",
      "name" : "KeyUsage",
      "title" : "WHO GDHCN  Key Usage ValueSet",
      "status" : "active",
      "experimental" : true,
      "date" : "2025-05-07T08:17:04+00:00",
      "jurisdiction" : [{
        "coding" : [{
          "system" : "http://unstats.un.org/unsd/methods/m49/m49.htm",
          "code" : "001"
        }]
      }],
      "expansion" : {
        "identifier" : "urn:uuid:57caa334-a832-48d8-9b87-28fe083af2d3",
        "timestamp" : "2025-05-07T08:21:18+00:00",
        "total" : 4,
        "offset" : 0,
        "parameter" : [{
          "name" : "displayLanguage",
          "valueCode" : "en-US"
        },
        {
          "name" : "count",
          "valueInteger" : 1000
        },
        {
          "name" : "offset",
          "valueInteger" : 0
        },
        {
          "name" : "excludeNested",
          "valueBoolean" : false
        },
        {
          "name" : "used-codesystem",
          "valueUri" : "http://smart.who.int/trust/CodeSystem/KeyUsage|1.1.6"
        }],
        "contains" : [{
          "system" : "http://smart.who.int/trust/CodeSystem/KeyUsage",
          "code" : "SCA",
          "display" : "Signing Certificate Authority"
        },
        {
          "system" : "http://smart.who.int/trust/CodeSystem/KeyUsage",
          "code" : "DSC",
          "display" : "Document Signing Certificate"
        },
        {
          "system" : "http://smart.who.int/trust/CodeSystem/KeyUsage",
          "code" : "UP",
          "display" : "Upload"
        },
        {
          "system" : "http://smart.who.int/trust/CodeSystem/KeyUsage",
          "code" : "TLS",
          "display" : "TLS"
        }]
      }
    }
  },
  {
    "fullUrl" : "http://smart.who.int/trust/ValueSet/PayloadTypes",
    "resource" : {
      "resourceType" : "ValueSet",
      "text" : {
        "status" : "generated",
        "div" : "<div xmlns=\"http://www.w3.org/1999/xhtml\"><p class=\"res-header-id\"><b>ValueSet </b></p><p style=\"border: black 1px dotted; background-color: #EEEEEE; padding: 8px; margin-bottom: 8px\">Expansion performed internally based on <a href=\"CodeSystem-PayloadTypes.html\">codesystem WHO GDHCN Payload Types v1.1.6 (CodeSystem)</a></p><p>This value set contains 1 concepts</p><table class=\"codes\"><tr><td style=\"white-space:nowrap\"><b>Code</b></td><td><b>System</b></td><td><b>Display (en-US)</b></td><td><b>Definition</b></td></tr><tr><td style=\"white-space:nowrap\"><a name=\"x-http://smart.who.int/trust/CodeSystem/PayloadTypes-urn:who:trust:trustlist:v2\"> </a>\u00a0\u00a0<a href=\"CodeSystem-PayloadTypes.html#PayloadTypes-urn.58who.58trust.58trustlist.58v2\">urn:who:trust:trustlist:v2</a></td><td>http://smart.who.int/trust/CodeSystem/PayloadTypes</td><td>WHO GDHCN Trust List v2</td><td><div><p>WHO Global Digital Health Certification Network (GDHCN) Trust List. Major release v2</p>\n</div></td></tr></table></div>"
      },
      "url" : "http://smart.who.int/trust/ValueSet/PayloadTypes",
      "version" : "1.1.6",
      "name" : "PayloadTypes",
      "title" : "WHO GDHCN Payload Types",
      "status" : "active",
      "experimental" : true,
      "date" : "2025-05-07T08:17:04+00:00",
      "jurisdiction" : [{
        "coding" : [{
          "system" : "http://unstats.un.org/unsd/methods/m49/m49.htm",
          "code" : "001"
        }]
      }],
      "expansion" : {
        "identifier" : "urn:uuid:736b8ad5-6a47-4a1c-80bf-5f720c8e9331",
        "timestamp" : "2025-05-07T08:21:19+00:00",
        "total" : 1,
        "offset" : 0,
        "parameter" : [{
          "name" : "displayLanguage",
          "valueCode" : "en-US"
        },
        {
          "name" : "count",
          "valueInteger" : 1000
        },
        {
          "name" : "offset",
          "valueInteger" : 0
        },
        {
          "name" : "excludeNested",
          "valueBoolean" : false
        },
        {
          "name" : "used-codesystem",
          "valueUri" : "http://smart.who.int/trust/CodeSystem/PayloadTypes|1.1.6"
        }],
        "contains" : [{
          "system" : "http://smart.who.int/trust/CodeSystem/PayloadTypes",
          "code" : "urn:who:trust:trustlist:v2",
          "display" : "WHO GDHCN Trust List v2"
        }]
      }
    }
  },
  {
    "fullUrl" : "http://smart.who.int/trust/ValueSet/Transactions",
    "resource" : {
      "resourceType" : "ValueSet",
      "text" : {
        "status" : "generated",
        "div" : "<div xmlns=\"http://www.w3.org/1999/xhtml\"><p class=\"res-header-id\"><b>ValueSet </b></p><p style=\"border: black 1px dotted; background-color: #EEEEEE; padding: 8px; margin-bottom: 8px\">Expansion performed internally based on <a href=\"CodeSystem-Transactions.html\">codesystem WHO GDHCN Transactions CodeSystem v1.1.6 (CodeSystem)</a></p><p>This value set contains 3 concepts</p><table class=\"codes\"><tr><td style=\"white-space:nowrap\"><b>Code</b></td><td><b>System</b></td><td><b>Display (en-US)</b></td></tr><tr><td style=\"white-space:nowrap\"><a name=\"x-http://smart.who.int/trust/CodeSystem/Transactions-keys-get-api\"> </a>\u00a0\u00a0<a href=\"CodeSystem-Transactions.html#Transactions-keys-get-api\">keys-get-api</a></td><td>http://smart.who.int/trust/CodeSystem/Transactions</td><td/></tr><tr><td style=\"white-space:nowrap\"><a name=\"x-http://smart.who.int/trust/CodeSystem/Transactions-keys-get-did\"> </a>\u00a0\u00a0<a href=\"CodeSystem-Transactions.html#Transactions-keys-get-did\">keys-get-did</a></td><td>http://smart.who.int/trust/CodeSystem/Transactions</td><td/></tr><tr><td style=\"white-space:nowrap\"><a name=\"x-http://smart.who.int/trust/CodeSystem/Transactions-keys-put-api\"> </a>\u00a0\u00a0<a href=\"CodeSystem-Transactions.html#Transactions-keys-put-api\">keys-put-api</a></td><td>http://smart.who.int/trust/CodeSystem/Transactions</td><td/></tr></table></div>"
      },
      "url" : "http://smart.who.int/trust/ValueSet/Transactions",
      "version" : "1.1.6",
      "name" : "Transactions",
      "title" : "WHO GDHCN Transaction Codes",
      "status" : "active",
      "experimental" : true,
      "date" : "2025-05-07T08:17:04+00:00",
      "jurisdiction" : [{
        "coding" : [{
          "system" : "http://unstats.un.org/unsd/methods/m49/m49.htm",
          "code" : "001"
        }]
      }],
      "expansion" : {
        "identifier" : "urn:uuid:f7984f5b-fb52-4446-85a3-c72ef2ef99f9",
        "timestamp" : "2025-05-07T08:21:20+00:00",
        "total" : 3,
        "offset" : 0,
        "parameter" : [{
          "name" : "displayLanguage",
          "valueCode" : "en-US"
        },
        {
          "name" : "count",
          "valueInteger" : 1000
        },
        {
          "name" : "offset",
          "valueInteger" : 0
        },
        {
          "name" : "excludeNested",
          "valueBoolean" : false
        },
        {
          "name" : "used-codesystem",
          "valueUri" : "http://smart.who.int/trust/CodeSystem/Transactions|1.1.6"
        }],
        "contains" : [{
          "system" : "http://smart.who.int/trust/CodeSystem/Transactions",
          "code" : "keys-get-api"
        },
        {
          "system" : "http://smart.who.int/trust/CodeSystem/Transactions",
          "code" : "keys-get-did"
        },
        {
          "system" : "http://smart.who.int/trust/CodeSystem/Transactions",
          "code" : "keys-put-api"
        }]
      }
    }
  }]
}