{
  "resourceType" : "ValueSet",
  "id" : "6f6dffd9-438b-454c-b1e1-98511611fdae-15",
  "url" : "http://hl7.org/fhir/comparison/ValueSet/6f6dffd9-438b-454c-b1e1-98511611fdae-15",
  "name" : "IntersectionWHO_TRUST_ACTORAndWHO_TRUST_ACTOR",
  "title" : "Intersection of TRUST.ACTOR ValueSet of key usage codes  And TRUST.ACTOR ValueSet of key usage codes ",
  "status" : "active",
  "date" : "2024-12-19T12:44:55+00:00",
  "jurisdiction" : [{
    "coding" : [{
      "system" : "http://unstats.un.org/unsd/methods/m49/m49.htm",
      "code" : "001"
    }]
  }]
}