{
   "library" : {
      "localId" : "0",
      "annotation" : [ {
         "translatorOptions" : "EnableAnnotations,EnableLocators,DisableListDemotion,DisableListPromotion",
         "signatureLevel" : "Overloads",
         "type" : "CqlToElmInfo"
      }, {
         "message" : "An operand identifier [reference] is hiding another identifier of the same name.",
         "errorType" : "semantic",
         "errorSeverity" : "warning",
         "type" : "CqlToElmError"
      }, {
         "message" : "An operand identifier [reference] is hiding another identifier of the same name.",
         "errorType" : "semantic",
         "errorSeverity" : "warning",
         "type" : "CqlToElmError"
      }, {
         "message" : "An operand identifier [reference] is hiding another identifier of the same name.",
         "errorType" : "semantic",
         "errorSeverity" : "warning",
         "type" : "CqlToElmError"
      }, {
         "type" : "Annotation",
         "s" : {
            "r" : "261",
            "s" : [ {
               "value" : [ "/**\n * Library: HIV.IND.15 Logic\n * Ref No: PRV.15\n * Short Name: VMMC scale-up\n *\n * Definition: Total number of voluntary medical male circumcisions (VMMCs) performed according to national standard during the reporting period\n *\n * Numerator: Total number of people undergoing VMMC performed according to national standard during the reporting period\n * Numerator Calculation: COUNT of clients with a \"VMMC procedure date\" in the reporting period\n * Numerator Exclusions: \n *\n * Denominator: 1\n * Denominator Calculation: 1\n * Denominator Exclusions: \n *\n * Disaggregations:\n * • Age (0–4, 5–9, 10–14, 15–19, 20–24, 25–49, 50+ years) \n *  • HIV status (positive, negative) \n *  • Provider type (key population-led or community-led organization, public sector provider, other entities such as private for-profit and not-for-profit organizations, including faith- based, international, nongovernmental) \n *  • Setting: facility-based service (including hospitals, health clinics, general practice offices, etc.) or community-based service (including drop-in centres, community service delivery points, mobile clinics or vans, outreach teams, community support groups, etc.) \n *  • Cities and other administrative regions of epidemiologic importance\n *\n * Disaggregation Elements: Age | HIV status\n *\n * Numerator and Denominator Elements:\n * VMMC procedure date\n *\n * Reference: Consolidated guidelines on person-centred HIV strategic information: strengthening routine data for impact. Geneva: World Health Organization; 2022\n * \n * Data Concepts:\n * HIV.A.DE17: Age | Calculated age (number of years) of the client based on date of birth\n * HIV.B.DE115: HIV status | HIV status reported after applying the national HIV testing algorithm. No single HIV test can provide an HIV-positive diagnosis.\n * HIV.B.DE116: HIV-positive | Client is HIV-positive\n * HIV.B.DE117: HIV-negative | Client is HIV-negative\n * HIV.B.DE118: Unknown | Client has unknown HIV status\n * HIV.B.DE198: VMMC procedure date | Date on which a voluntary medical male circumcision procedure was performed\n *\n * Additional Context\n * - what it measures: This indicator measures progress in scaling up male circumcision services.\n * - rationale: WHO and UNAIDS recommend VMMC as an efficacious intervention for HIV prevention in priority* countries and regions with high HIV prevalence and low male circumcision prevalence. |  | Randomized controlled trials have shown that VMMC provided by trained health professionals with proper equipment can reduce the risk of men heterosexually acquiring HIV infection.\n * - method: Individual-level data obtained from programme records (for example, VMMC registers).   |  | The recommended reporting period is 12 months.\n * \n * Suggested Scoring Method: continuous-variable | http://hl7.org/fhir/us/cqfmeasures/StructureDefinition/cv-measure-cqfm\n */\n\n","library HIVIND15Logic" ]
            } ]
         }
      } ],
      "identifier" : {
         "id" : "HIVIND15Logic",
         "system" : "http://smart.who.int/hiv"
      },
      "schemaIdentifier" : {
         "id" : "urn:hl7-org:elm",
         "version" : "r1"
      },
      "usings" : {
         "def" : [ {
            "localId" : "1",
            "localIdentifier" : "System",
            "uri" : "urn:hl7-org:elm-types:r1"
         }, {
            "localId" : "206",
            "locator" : "49:1-49:26",
            "localIdentifier" : "FHIR",
            "uri" : "http://hl7.org/fhir",
            "version" : "4.0.1",
            "annotation" : [ {
               "type" : "Annotation",
               "s" : {
                  "r" : "206",
                  "s" : [ {
                     "value" : [ "// Included Libraries\n","using " ]
                  }, {
                     "s" : [ {
                        "value" : [ "FHIR" ]
                     } ]
                  }, {
                     "value" : [ " version '4.0.1'" ]
                  } ]
               }
            } ]
         } ]
      },
      "includes" : {
         "def" : [ {
            "localId" : "207",
            "locator" : "51:1-51:44",
            "localIdentifier" : "HIC",
            "path" : "http://smart.who.int/hiv/HIVCommon",
            "version" : "0.0.1",
            "annotation" : [ {
               "type" : "Annotation",
               "s" : {
                  "r" : "207",
                  "s" : [ {
                     "value" : [ "","include " ]
                  }, {
                     "s" : [ {
                        "value" : [ "HIVCommon" ]
                     } ]
                  }, {
                     "value" : [ " version ","'0.0.1'"," called ","HIC" ]
                  } ]
               }
            } ]
         }, {
            "localId" : "208",
            "locator" : "52:1-52:35",
            "localIdentifier" : "FHIRHelpers",
            "path" : "http://hl7.org/fhir/FHIRHelpers",
            "version" : "4.0.1",
            "annotation" : [ {
               "type" : "Annotation",
               "s" : {
                  "r" : "208",
                  "s" : [ {
                     "value" : [ "","include " ]
                  }, {
                     "s" : [ {
                        "value" : [ "FHIRHelpers" ]
                     } ]
                  }, {
                     "value" : [ " version ","'4.0.1'" ]
                  } ]
               }
            } ]
         }, {
            "localId" : "209",
            "locator" : "53:1-53:29",
            "localIdentifier" : "WCom",
            "path" : "http://smart.who.int/hiv/WHOCommon",
            "annotation" : [ {
               "type" : "Annotation",
               "s" : {
                  "r" : "209",
                  "s" : [ {
                     "value" : [ "","include " ]
                  }, {
                     "s" : [ {
                        "value" : [ "WHOCommon" ]
                     } ]
                  }, {
                     "value" : [ " called ","WCom" ]
                  } ]
               }
            } ]
         }, {
            "localId" : "210",
            "locator" : "55:1-55:39",
            "localIdentifier" : "HIE",
            "path" : "http://smart.who.int/hiv/HIVIndicatorElements",
            "annotation" : [ {
               "type" : "Annotation",
               "s" : {
                  "r" : "210",
                  "s" : [ {
                     "value" : [ "","include " ]
                  }, {
                     "s" : [ {
                        "value" : [ "HIVIndicatorElements" ]
                     } ]
                  }, {
                     "value" : [ " called ","HIE" ]
                  } ]
               }
            } ]
         } ]
      },
      "parameters" : {
         "def" : [ {
            "localId" : "211",
            "locator" : "57:1-57:88",
            "name" : "Measurement Period",
            "accessLevel" : "Public",
            "annotation" : [ {
               "type" : "Annotation",
               "s" : {
                  "r" : "211",
                  "s" : [ {
                     "value" : [ "// Indicator Definition\n","parameter ","\"Measurement Period\""," " ]
                  }, {
                     "r" : "223",
                     "s" : [ {
                        "value" : [ "Interval<" ]
                     }, {
                        "r" : "224",
                        "s" : [ {
                           "value" : [ "Date" ]
                        } ]
                     }, {
                        "value" : [ ">" ]
                     } ]
                  }, {
                     "value" : [ " default " ]
                  }, {
                     "r" : "222",
                     "s" : [ {
                        "r" : "216",
                        "value" : [ "Interval[","@2023-01-01",", ","@2023-01-30","]" ]
                     } ]
                  } ]
               }
            } ],
            "default" : {
               "localId" : "222",
               "locator" : "57:55-57:88",
               "lowClosed" : true,
               "highClosed" : true,
               "type" : "Interval",
               "low" : {
                  "localId" : "216",
                  "locator" : "57:64-57:74",
                  "type" : "Date",
                  "signature" : [ ],
                  "year" : {
                     "localId" : "213",
                     "valueType" : "{urn:hl7-org:elm-types:r1}Integer",
                     "value" : "2023",
                     "type" : "Literal"
                  },
                  "month" : {
                     "localId" : "214",
                     "valueType" : "{urn:hl7-org:elm-types:r1}Integer",
                     "value" : "1",
                     "type" : "Literal"
                  },
                  "day" : {
                     "localId" : "215",
                     "valueType" : "{urn:hl7-org:elm-types:r1}Integer",
                     "value" : "1",
                     "type" : "Literal"
                  }
               },
               "high" : {
                  "localId" : "221",
                  "locator" : "57:77-57:87",
                  "type" : "Date",
                  "signature" : [ ],
                  "year" : {
                     "localId" : "218",
                     "valueType" : "{urn:hl7-org:elm-types:r1}Integer",
                     "value" : "2023",
                     "type" : "Literal"
                  },
                  "month" : {
                     "localId" : "219",
                     "valueType" : "{urn:hl7-org:elm-types:r1}Integer",
                     "value" : "1",
                     "type" : "Literal"
                  },
                  "day" : {
                     "localId" : "220",
                     "valueType" : "{urn:hl7-org:elm-types:r1}Integer",
                     "value" : "30",
                     "type" : "Literal"
                  }
               }
            },
            "parameterTypeSpecifier" : {
               "localId" : "223",
               "locator" : "57:32-57:45",
               "type" : "IntervalTypeSpecifier",
               "pointType" : {
                  "localId" : "224",
                  "locator" : "57:41-57:44",
                  "name" : "{urn:hl7-org:elm-types:r1}Date",
                  "type" : "NamedTypeSpecifier"
               }
            }
         } ]
      },
      "contexts" : {
         "def" : [ {
            "localId" : "228",
            "locator" : "59:1-59:15",
            "name" : "Patient"
         } ]
      },
      "statements" : {
         "def" : [ {
            "localId" : "226",
            "locator" : "59:1-59:15",
            "name" : "Patient",
            "context" : "Patient",
            "expression" : {
               "localId" : "227",
               "type" : "SingletonFrom",
               "signature" : [ ],
               "operand" : {
                  "localId" : "225",
                  "locator" : "59:1-59:15",
                  "dataType" : "{http://hl7.org/fhir}Patient",
                  "templateId" : "http://hl7.org/fhir/StructureDefinition/Patient",
                  "type" : "Retrieve",
                  "include" : [ ],
                  "codeFilter" : [ ],
                  "dateFilter" : [ ],
                  "otherFilter" : [ ]
               }
            }
         }, {
            "localId" : "230",
            "locator" : "66:1-67:6",
            "name" : "Initial Population",
            "context" : "Patient",
            "accessLevel" : "Public",
            "annotation" : [ {
               "type" : "Annotation",
               "s" : {
                  "r" : "230",
                  "s" : [ {
                     "r" : "231",
                     "value" : [ "/* Populations */\n\n/*\n *Initial Population\n */\n\n","define ","\"Initial Population\"",":\n  ","true" ]
                  } ]
               }
            } ],
            "expression" : {
               "localId" : "231",
               "locator" : "67:3-67:6",
               "valueType" : "{urn:hl7-org:elm-types:r1}Boolean",
               "value" : "true",
               "type" : "Literal"
            }
         }, {
            "localId" : "233",
            "locator" : "76:1-77:12",
            "name" : "Measure Population",
            "context" : "Patient",
            "accessLevel" : "Public",
            "annotation" : [ {
               "type" : "Annotation",
               "s" : {
                  "r" : "233",
                  "s" : [ {
                     "value" : [ "/**\n * Measure Population\n *\n * Definition: Total number of people undergoing VMMC performed according to national standard during the reporting period\n * Calculation: Total number of people undergoing VMMC performed according to national standard during the reporting period\n */\n                                                       \n","define ","\"Measure Population\"",":\n  " ]
                  }, {
                     "r" : "235",
                     "s" : [ {
                        "r" : "234",
                        "s" : [ {
                           "value" : [ "HIE" ]
                        } ]
                     }, {
                        "value" : [ "." ]
                     }, {
                        "r" : "235",
                        "s" : [ {
                           "value" : [ "\"VMMC\"" ]
                        } ]
                     } ]
                  } ]
               }
            } ],
            "expression" : {
               "localId" : "235",
               "locator" : "77:3-77:12",
               "name" : "VMMC",
               "libraryName" : "HIE",
               "type" : "ExpressionRef"
            }
         }, {
            "localId" : "236",
            "locator" : "85:1-86:3",
            "name" : "Measure Observation",
            "context" : "Patient",
            "accessLevel" : "Public",
            "type" : "FunctionDef",
            "annotation" : [ {
               "type" : "Annotation",
               "s" : {
                  "r" : "236",
                  "s" : [ {
                     "value" : [ "/**\n * Measure Observation\n * Definition: Total number of people undergoing VMMC performed according to national standard during the reporting period\n * Calculation: Total number of people undergoing VMMC performed according to national standard during the reporting period                                                      \n */     \n\n","define function \"Measure Observation\"(Patient \"Patient\"):\n  " ]
                  }, {
                     "r" : "239",
                     "s" : [ {
                        "r" : "239",
                        "value" : [ "1" ]
                     } ]
                  } ]
               }
            } ],
            "expression" : {
               "localId" : "239",
               "locator" : "86:3",
               "valueType" : "{urn:hl7-org:elm-types:r1}Integer",
               "value" : "1",
               "type" : "Literal"
            },
            "operand" : [ {
               "localId" : "238",
               "name" : "Patient",
               "operandTypeSpecifier" : {
                  "localId" : "237",
                  "locator" : "85:47-85:55",
                  "name" : "{http://hl7.org/fhir}Patient",
                  "type" : "NamedTypeSpecifier"
               }
            } ]
         }, {
            "localId" : "241",
            "locator" : "94:1-95:42",
            "name" : "Administrative Gender Stratifier",
            "context" : "Patient",
            "accessLevel" : "Public",
            "annotation" : [ {
               "type" : "Annotation",
               "s" : {
                  "r" : "241",
                  "s" : [ {
                     "value" : [ "/* end Populations */\n\n\n/*\n * Disaggregators\n */\n\n","define ","\"Administrative Gender Stratifier\"",":\n\t" ]
                  }, {
                     "r" : "243",
                     "s" : [ {
                        "r" : "242",
                        "s" : [ {
                           "value" : [ "HIE" ]
                        } ]
                     }, {
                        "value" : [ "." ]
                     }, {
                        "r" : "243",
                        "s" : [ {
                           "value" : [ "\"By Administrative Gender Stratifier\"" ]
                        } ]
                     } ]
                  } ]
               }
            } ],
            "expression" : {
               "localId" : "243",
               "locator" : "95:2-95:42",
               "name" : "By Administrative Gender Stratifier",
               "libraryName" : "HIE",
               "type" : "ExpressionRef"
            }
         }, {
            "localId" : "245",
            "locator" : "97:1-98:26",
            "name" : "Age Stratifier",
            "context" : "Patient",
            "accessLevel" : "Public",
            "annotation" : [ {
               "type" : "Annotation",
               "s" : {
                  "r" : "245",
                  "s" : [ {
                     "value" : [ "","define ","\"Age Stratifier\"",":\n\t" ]
                  }, {
                     "r" : "247",
                     "s" : [ {
                        "r" : "246",
                        "s" : [ {
                           "value" : [ "HIE" ]
                        } ]
                     }, {
                        "value" : [ "." ]
                     }, {
                        "r" : "247",
                        "s" : [ {
                           "value" : [ "\"By Age Stratifier 2\"" ]
                        } ]
                     } ]
                  } ]
               }
            } ],
            "expression" : {
               "localId" : "247",
               "locator" : "98:2-98:26",
               "name" : "By Age Stratifier 2",
               "libraryName" : "HIE",
               "type" : "ExpressionRef"
            }
         }, {
            "localId" : "249",
            "locator" : "100:1-101:38",
            "name" : "Geographic Region Stratifier",
            "context" : "Patient",
            "accessLevel" : "Public",
            "annotation" : [ {
               "type" : "Annotation",
               "s" : {
                  "r" : "249",
                  "s" : [ {
                     "value" : [ "","define ","\"Geographic Region Stratifier\"",":\n\t" ]
                  }, {
                     "r" : "251",
                     "s" : [ {
                        "r" : "250",
                        "s" : [ {
                           "value" : [ "HIE" ]
                        } ]
                     }, {
                        "value" : [ "." ]
                     }, {
                        "r" : "251",
                        "s" : [ {
                           "value" : [ "\"By Geographic Region Stratifier\"" ]
                        } ]
                     } ]
                  } ]
               }
            } ],
            "expression" : {
               "localId" : "251",
               "locator" : "101:2-101:38",
               "name" : "By Geographic Region Stratifier",
               "libraryName" : "HIE",
               "type" : "ExpressionRef"
            }
         }, {
            "localId" : "253",
            "locator" : "103:1-104:17",
            "name" : "Setting",
            "context" : "Patient",
            "accessLevel" : "Public",
            "annotation" : [ {
               "type" : "Annotation",
               "s" : {
                  "r" : "253",
                  "s" : [ {
                     "value" : [ "","define ","\"Setting\"",":\n    " ]
                  }, {
                     "r" : "255",
                     "s" : [ {
                        "r" : "254",
                        "s" : [ {
                           "value" : [ "HIE" ]
                        } ]
                     }, {
                        "value" : [ "." ]
                     }, {
                        "r" : "255",
                        "s" : [ {
                           "value" : [ "\"setting\"" ]
                        } ]
                     } ]
                  } ]
               }
            } ],
            "expression" : {
               "localId" : "255",
               "locator" : "104:5-104:17",
               "name" : "setting",
               "libraryName" : "HIE",
               "type" : "ExpressionRef"
            }
         }, {
            "localId" : "257",
            "locator" : "106:1-107:31",
            "name" : "HIV Status",
            "context" : "Patient",
            "accessLevel" : "Public",
            "annotation" : [ {
               "type" : "Annotation",
               "s" : {
                  "r" : "257",
                  "s" : [ {
                     "value" : [ "","define ","\"HIV Status\"",":\n    " ]
                  }, {
                     "r" : "259",
                     "s" : [ {
                        "r" : "258",
                        "s" : [ {
                           "value" : [ "HIE" ]
                        } ]
                     }, {
                        "value" : [ "." ]
                     }, {
                        "r" : "259",
                        "s" : [ {
                           "value" : [ "\"HIV Status Stratifier\"" ]
                        } ]
                     } ]
                  } ]
               }
            } ],
            "expression" : {
               "localId" : "259",
               "locator" : "107:5-107:31",
               "name" : "HIV Status Stratifier",
               "libraryName" : "HIE",
               "type" : "ExpressionRef"
            }
         }, {
            "localId" : "261",
            "locator" : "111:1-116:40",
            "name" : "Stratification",
            "context" : "Patient",
            "accessLevel" : "Public",
            "annotation" : [ {
               "type" : "Annotation",
               "s" : {
                  "r" : "261",
                  "s" : [ {
                     "value" : [ "//provider type not provided?\n\n","define ","\"Stratification\"",":\n " ]
                  }, {
                     "r" : "312",
                     "s" : [ {
                        "r" : "306",
                        "s" : [ {
                           "r" : "302",
                           "s" : [ {
                              "r" : "296",
                              "s" : [ {
                                 "r" : "292",
                                 "s" : [ {
                                    "r" : "285",
                                    "s" : [ {
                                       "r" : "281",
                                       "s" : [ {
                                          "r" : "276",
                                          "s" : [ {
                                             "r" : "272",
                                             "s" : [ {
                                                "r" : "271",
                                                "s" : [ {
                                                   "r" : "270",
                                                   "s" : [ {
                                                      "value" : [ "HIE" ]
                                                   } ]
                                                }, {
                                                   "value" : [ "." ]
                                                }, {
                                                   "r" : "271",
                                                   "s" : [ {
                                                      "value" : [ "\"By Administrative Gender Stratifier\"" ]
                                                   } ]
                                                } ]
                                             }, {
                                                "value" : [ "." ]
                                             }, {
                                                "r" : "272",
                                                "s" : [ {
                                                   "value" : [ "code" ]
                                                } ]
                                             } ]
                                          }, {
                                             "value" : [ " \n  + " ]
                                          }, {
                                             "r" : "273",
                                             "s" : [ {
                                                "value" : [ "':'" ]
                                             } ]
                                          } ]
                                       }, {
                                          "value" : [ " + " ]
                                       }, {
                                          "r" : "278",
                                          "s" : [ {
                                             "r" : "277",
                                             "s" : [ {
                                                "value" : [ "HIE" ]
                                             } ]
                                          }, {
                                             "value" : [ "." ]
                                          }, {
                                             "r" : "278",
                                             "s" : [ {
                                                "value" : [ "\"By Age Stratifier 2\"" ]
                                             } ]
                                          } ]
                                       } ]
                                    }, {
                                       "value" : [ "\n+ " ]
                                    }, {
                                       "r" : "282",
                                       "s" : [ {
                                          "value" : [ "':'" ]
                                       } ]
                                    } ]
                                 }, {
                                    "value" : [ " + " ]
                                 }, {
                                    "r" : "287",
                                    "s" : [ {
                                       "r" : "286",
                                       "s" : [ {
                                          "value" : [ "HIE" ]
                                       } ]
                                    }, {
                                       "value" : [ "." ]
                                    }, {
                                       "r" : "287",
                                       "s" : [ {
                                          "value" : [ "\"By Geographic Region Stratifier\"" ]
                                       } ]
                                    } ]
                                 } ]
                              }, {
                                 "value" : [ "\n + " ]
                              }, {
                                 "r" : "293",
                                 "s" : [ {
                                    "value" : [ "':'" ]
                                 } ]
                              } ]
                           }, {
                              "value" : [ " + " ]
                           }, {
                              "r" : "299",
                              "s" : [ {
                                 "r" : "298",
                                 "s" : [ {
                                    "r" : "297",
                                    "s" : [ {
                                       "value" : [ "HIE" ]
                                    } ]
                                 }, {
                                    "value" : [ "." ]
                                 }, {
                                    "r" : "298",
                                    "s" : [ {
                                       "value" : [ "\"setting\"" ]
                                    } ]
                                 } ]
                              }, {
                                 "value" : [ "." ]
                              }, {
                                 "r" : "299",
                                 "s" : [ {
                                    "value" : [ "code" ]
                                 } ]
                              } ]
                           } ]
                        }, {
                           "value" : [ "\n+ " ]
                        }, {
                           "r" : "303",
                           "s" : [ {
                              "value" : [ "':'" ]
                           } ]
                        } ]
                     }, {
                        "value" : [ " + " ]
                     }, {
                        "r" : "309",
                        "s" : [ {
                           "r" : "308",
                           "s" : [ {
                              "r" : "307",
                              "s" : [ {
                                 "value" : [ "HIE" ]
                              } ]
                           }, {
                              "value" : [ "." ]
                           }, {
                              "r" : "308",
                              "s" : [ {
                                 "value" : [ "\"HIV Status Stratifier\"" ]
                              } ]
                           } ]
                        }, {
                           "value" : [ "." ]
                        }, {
                           "r" : "309",
                           "s" : [ {
                              "value" : [ "code" ]
                           } ]
                        } ]
                     } ]
                  } ]
               }
            } ],
            "expression" : {
               "localId" : "312",
               "locator" : "112:2-116:40",
               "type" : "Concatenate",
               "signature" : [ ],
               "operand" : [ {
                  "localId" : "306",
                  "locator" : "112:2-116:5",
                  "type" : "Concatenate",
                  "signature" : [ ],
                  "operand" : [ {
                     "localId" : "302",
                     "locator" : "112:2-115:27",
                     "type" : "Concatenate",
                     "signature" : [ ],
                     "operand" : [ {
                        "localId" : "296",
                        "locator" : "112:2-115:6",
                        "type" : "Concatenate",
                        "signature" : [ ],
                        "operand" : [ {
                           "localId" : "292",
                           "locator" : "112:2-114:45",
                           "type" : "Concatenate",
                           "signature" : [ ],
                           "operand" : [ {
                              "localId" : "285",
                              "locator" : "112:2-114:5",
                              "type" : "Concatenate",
                              "signature" : [ ],
                              "operand" : [ {
                                 "localId" : "281",
                                 "locator" : "112:2-113:35",
                                 "type" : "Concatenate",
                                 "signature" : [ ],
                                 "operand" : [ {
                                    "localId" : "276",
                                    "locator" : "112:2-113:7",
                                    "type" : "Concatenate",
                                    "signature" : [ ],
                                    "operand" : [ {
                                       "localId" : "272",
                                       "locator" : "112:2-112:47",
                                       "path" : "code",
                                       "type" : "Property",
                                       "source" : {
                                          "localId" : "271",
                                          "locator" : "112:2-112:42",
                                          "name" : "By Administrative Gender Stratifier",
                                          "libraryName" : "HIE",
                                          "type" : "ExpressionRef"
                                       }
                                    }, {
                                       "localId" : "273",
                                       "locator" : "113:5-113:7",
                                       "valueType" : "{urn:hl7-org:elm-types:r1}String",
                                       "value" : ":",
                                       "type" : "Literal"
                                    } ]
                                 }, {
                                    "localId" : "278",
                                    "locator" : "113:11-113:35",
                                    "name" : "By Age Stratifier 2",
                                    "libraryName" : "HIE",
                                    "type" : "ExpressionRef"
                                 } ]
                              }, {
                                 "localId" : "282",
                                 "locator" : "114:3-114:5",
                                 "valueType" : "{urn:hl7-org:elm-types:r1}String",
                                 "value" : ":",
                                 "type" : "Literal"
                              } ]
                           }, {
                              "localId" : "288",
                              "name" : "ToString",
                              "libraryName" : "FHIRHelpers",
                              "type" : "FunctionRef",
                              "signature" : [ {
                                 "localId" : "289",
                                 "name" : "{http://hl7.org/fhir}string",
                                 "type" : "NamedTypeSpecifier"
                              } ],
                              "operand" : [ {
                                 "localId" : "287",
                                 "locator" : "114:9-114:45",
                                 "name" : "By Geographic Region Stratifier",
                                 "libraryName" : "HIE",
                                 "type" : "ExpressionRef"
                              } ]
                           } ]
                        }, {
                           "localId" : "293",
                           "locator" : "115:4-115:6",
                           "valueType" : "{urn:hl7-org:elm-types:r1}String",
                           "value" : ":",
                           "type" : "Literal"
                        } ]
                     }, {
                        "localId" : "299",
                        "locator" : "115:10-115:27",
                        "path" : "code",
                        "type" : "Property",
                        "source" : {
                           "localId" : "298",
                           "locator" : "115:10-115:22",
                           "name" : "setting",
                           "libraryName" : "HIE",
                           "type" : "ExpressionRef"
                        }
                     } ]
                  }, {
                     "localId" : "303",
                     "locator" : "116:3-116:5",
                     "valueType" : "{urn:hl7-org:elm-types:r1}String",
                     "value" : ":",
                     "type" : "Literal"
                  } ]
               }, {
                  "localId" : "309",
                  "locator" : "116:9-116:40",
                  "path" : "code",
                  "type" : "Property",
                  "source" : {
                     "localId" : "308",
                     "locator" : "116:9-116:35",
                     "name" : "HIV Status Stratifier",
                     "libraryName" : "HIE",
                     "type" : "ExpressionRef"
                  }
               } ]
            }
         } ]
      }
   }
}