{
  "date" : "Fri, 20 Dec, 2024 06:07:24 +0000",
  "doco" : "For each file: start is seconds after start activity occurred. Length = milliseconds activity took",
  "files" : [
    {
      "name" : "/fsh-generated/resources/ImplementationGuide-smart.who.int.trust.json",
      "size" : 13165,
      "processes" : [
        {
          "activity" : "load",
          "start" : 221,
          "length" : 7
        },
        {
          "activity" : "checkR4R4B",
          "start" : 221,
          "length" : 2
        },
        {
          "activity" : "generateNarratives",
          "start" : 221,
          "length" : 128
        },
        {
          "activity" : "validate",
          "start" : 224,
          "length" : 6623
        },
        {
          "activity" : "generate1",
          "start" : 247,
          "length" : 89
        },
        {
          "activity" : "generate2",
          "start" : 249,
          "length" : 35
        },
        {
          "activity" : "generateValidationPack",
          "start" : 284,
          "length" : 3
        },
        {
          "activity" : "scanExamplesForR5",
          "start" : 297,
          "length" : 1
        }
      ]
    },
    {
      "name" : "fsh-generated/resources/CodeSystem-WHO.TRUST.ACTOR.json",
      "size" : 1054,
      "processes" : [
        {
          "activity" : "loadResources",
          "start" : 221,
          "length" : 4
        },
        {
          "activity" : "load-configure",
          "start" : 221,
          "length" : 1
        },
        {
          "activity" : "load",
          "start" : 221,
          "length" : 5
        },
        {
          "activity" : "generateNarratives",
          "start" : 222,
          "length" : 11
        },
        {
          "activity" : "validate",
          "start" : 222,
          "length" : 1267
        },
        {
          "activity" : "generate1",
          "start" : 247,
          "length" : 19
        },
        {
          "activity" : "generate2",
          "start" : 250,
          "length" : 4786
        },
        {
          "activity" : "generateValidationPack",
          "start" : 284,
          "length" : 1
        }
      ]
    },
    {
      "name" : "fsh-generated/resources/CodeSystem-WHO.TRUST.DOMAIN.json",
      "size" : 589,
      "processes" : [
        {
          "activity" : "loadResources",
          "start" : 221,
          "length" : 4
        },
        {
          "activity" : "load",
          "start" : 221,
          "length" : 4
        },
        {
          "activity" : "generateNarratives",
          "start" : 222,
          "length" : 9
        },
        {
          "activity" : "validate",
          "start" : 223,
          "length" : 12
        },
        {
          "activity" : "generate1",
          "start" : 247,
          "length" : 15
        },
        {
          "activity" : "generate2",
          "start" : 254,
          "length" : 106
        }
      ]
    },
    {
      "name" : "fsh-generated/resources/CodeSystem-WHO.TRUST.KEYUSAGE.json",
      "size" : 1547,
      "processes" : [
        {
          "activity" : "loadResources",
          "start" : 221,
          "length" : 4
        },
        {
          "activity" : "load",
          "start" : 221,
          "length" : 4
        },
        {
          "activity" : "generateNarratives",
          "start" : 222,
          "length" : 10
        },
        {
          "activity" : "validate",
          "start" : 223,
          "length" : 11
        },
        {
          "activity" : "generate1",
          "start" : 247,
          "length" : 20
        },
        {
          "activity" : "generate2",
          "start" : 254,
          "length" : 107
        }
      ]
    },
    {
      "name" : "fsh-generated/resources/CodeSystem-WHO.TRUST.TRANSACTION.json",
      "size" : 686,
      "processes" : [
        {
          "activity" : "loadResources",
          "start" : 221,
          "length" : 4
        },
        {
          "activity" : "load",
          "start" : 221,
          "length" : 4
        },
        {
          "activity" : "generateNarratives",
          "start" : 222,
          "length" : 10
        },
        {
          "activity" : "validate",
          "start" : 223,
          "length" : 11
        },
        {
          "activity" : "generate1",
          "start" : 247,
          "length" : 17
        },
        {
          "activity" : "generate2",
          "start" : 255,
          "length" : 103
        },
        {
          "activity" : "generateValidationPack",
          "start" : 284,
          "length" : 1
        }
      ]
    },
    {
      "name" : "fsh-generated/resources/StructureDefinition-COSEHeader.json",
      "size" : 1440,
      "processes" : [
        {
          "activity" : "loadResources",
          "start" : 221,
          "length" : 3
        },
        {
          "activity" : "load",
          "start" : 221,
          "length" : 5
        },
        {
          "activity" : "generateSnapshots",
          "start" : 221,
          "length" : 5
        },
        {
          "activity" : "generateNarratives",
          "start" : 222,
          "length" : 12
        },
        {
          "activity" : "validate",
          "start" : 223,
          "length" : 76
        },
        {
          "activity" : "generate1",
          "start" : 247,
          "length" : 41
        },
        {
          "activity" : "generate2",
          "start" : 255,
          "length" : 97
        }
      ]
    },
    {
      "name" : "fsh-generated/resources/StructureDefinition-CWT.json",
      "size" : 1726,
      "processes" : [
        {
          "activity" : "loadResources",
          "start" : 221,
          "length" : 4
        },
        {
          "activity" : "load",
          "start" : 221,
          "length" : 4
        },
        {
          "activity" : "generateSnapshots",
          "start" : 221,
          "length" : 5
        },
        {
          "activity" : "generateNarratives",
          "start" : 222,
          "length" : 14
        },
        {
          "activity" : "validate",
          "start" : 223,
          "length" : 52
        },
        {
          "activity" : "generate1",
          "start" : 247,
          "length" : 49
        },
        {
          "activity" : "generate2",
          "start" : 255,
          "length" : 93
        },
        {
          "activity" : "generateValidationPack",
          "start" : 284,
          "length" : 1
        }
      ]
    },
    {
      "name" : "fsh-generated/resources/StructureDefinition-CWTPayload.json",
      "size" : 2091,
      "processes" : [
        {
          "activity" : "loadResources",
          "start" : 221,
          "length" : 4
        },
        {
          "activity" : "load",
          "start" : 221,
          "length" : 4
        },
        {
          "activity" : "generateSnapshots",
          "start" : 221,
          "length" : 4
        },
        {
          "activity" : "generateNarratives",
          "start" : 222,
          "length" : 12
        },
        {
          "activity" : "validate",
          "start" : 223,
          "length" : 81
        },
        {
          "activity" : "generate1",
          "start" : 247,
          "length" : 57
        },
        {
          "activity" : "generate2",
          "start" : 255,
          "length" : 82
        },
        {
          "activity" : "generateValidationPack",
          "start" : 284,
          "length" : 1
        }
      ]
    },
    {
      "name" : "fsh-generated/resources/StructureDefinition-HCert.json",
      "size" : 2605,
      "processes" : [
        {
          "activity" : "loadResources",
          "start" : 221,
          "length" : 4
        },
        {
          "activity" : "load-configure",
          "start" : 221,
          "length" : 1
        },
        {
          "activity" : "load",
          "start" : 221,
          "length" : 5
        },
        {
          "activity" : "generateSnapshots",
          "start" : 221,
          "length" : 5
        },
        {
          "activity" : "generateNarratives",
          "start" : 222,
          "length" : 12
        },
        {
          "activity" : "validate",
          "start" : 223,
          "length" : 107
        },
        {
          "activity" : "generate1",
          "start" : 247,
          "length" : 83
        },
        {
          "activity" : "generate2",
          "start" : 255,
          "length" : 105
        },
        {
          "activity" : "generateValidationPack",
          "start" : 284,
          "length" : 1
        }
      ]
    },
    {
      "name" : "fsh-generated/resources/StructureDefinition-SchemeInformation.json",
      "size" : 7680,
      "processes" : [
        {
          "activity" : "loadResources",
          "start" : 221,
          "length" : 4
        },
        {
          "activity" : "load",
          "start" : 221,
          "length" : 5
        },
        {
          "activity" : "generateSnapshots",
          "start" : 221,
          "length" : 15
        },
        {
          "activity" : "generateNarratives",
          "start" : 222,
          "length" : 21
        },
        {
          "activity" : "validate",
          "start" : 223,
          "length" : 410
        },
        {
          "activity" : "scanForUsageStats",
          "start" : 247,
          "length" : 1
        },
        {
          "activity" : "generate1",
          "start" : 247,
          "length" : 165
        },
        {
          "activity" : "generate2",
          "start" : 255,
          "length" : 286
        },
        {
          "activity" : "generateValidationPack",
          "start" : 284,
          "length" : 4
        }
      ]
    },
    {
      "name" : "fsh-generated/resources/StructureDefinition-SmartHealthLink.json",
      "size" : 1401,
      "processes" : [
        {
          "activity" : "loadResources",
          "start" : 221,
          "length" : 4
        },
        {
          "activity" : "load",
          "start" : 221,
          "length" : 4
        },
        {
          "activity" : "generateSnapshots",
          "start" : 221,
          "length" : 4
        },
        {
          "activity" : "generateNarratives",
          "start" : 222,
          "length" : 21
        },
        {
          "activity" : "validate",
          "start" : 224,
          "length" : 40
        },
        {
          "activity" : "generate1",
          "start" : 247,
          "length" : 36
        },
        {
          "activity" : "generate2",
          "start" : 255,
          "length" : 99
        }
      ]
    },
    {
      "name" : "fsh-generated/resources/StructureDefinition-SmartHealthLinkPayload.json",
      "size" : 5267,
      "processes" : [
        {
          "activity" : "loadResources",
          "start" : 221,
          "length" : 4
        },
        {
          "activity" : "load",
          "start" : 221,
          "length" : 5
        },
        {
          "activity" : "generateSnapshots",
          "start" : 221,
          "length" : 6
        },
        {
          "activity" : "generateNarratives",
          "start" : 222,
          "length" : 14
        },
        {
          "activity" : "validate",
          "start" : 224,
          "length" : 128
        },
        {
          "activity" : "generate1",
          "start" : 247,
          "length" : 78
        },
        {
          "activity" : "generate2",
          "start" : 255,
          "length" : 135
        },
        {
          "activity" : "generateValidationPack",
          "start" : 284,
          "length" : 2
        }
      ]
    },
    {
      "name" : "fsh-generated/resources/ValueSet-WHO.TRUST.ACTOR.json",
      "size" : 454,
      "processes" : [
        {
          "activity" : "loadResources",
          "start" : 221,
          "length" : 4
        },
        {
          "activity" : "load",
          "start" : 221,
          "length" : 5
        },
        {
          "activity" : "generateNarratives",
          "start" : 222,
          "length" : 62
        },
        {
          "activity" : "validate",
          "start" : 223,
          "length" : 19
        },
        {
          "activity" : "generate1",
          "start" : 247,
          "length" : 17
        },
        {
          "activity" : "generate2",
          "start" : 256,
          "length" : 9706
        }
      ]
    },
    {
      "name" : "fsh-generated/resources/ValueSet-WHO.TRUST.DOMAIN.json",
      "size" : 563,
      "processes" : [
        {
          "activity" : "loadResources",
          "start" : 221,
          "length" : 4
        },
        {
          "activity" : "scan",
          "start" : 221,
          "length" : 1
        },
        {
          "activity" : "load",
          "start" : 221,
          "length" : 4
        },
        {
          "activity" : "generateNarratives",
          "start" : 222,
          "length" : 6
        },
        {
          "activity" : "validate",
          "start" : 223,
          "length" : 13
        },
        {
          "activity" : "generate1",
          "start" : 247,
          "length" : 15
        },
        {
          "activity" : "generate2",
          "start" : 265,
          "length" : 130
        }
      ]
    },
    {
      "name" : "fsh-generated/resources/ValueSet-WHO.TRUST.KEYUSAGE.json",
      "size" : 868,
      "processes" : [
        {
          "activity" : "loadResources",
          "start" : 221,
          "length" : 4
        },
        {
          "activity" : "load",
          "start" : 221,
          "length" : 4
        },
        {
          "activity" : "generateNarratives",
          "start" : 222,
          "length" : 5
        },
        {
          "activity" : "validate",
          "start" : 223,
          "length" : 14
        },
        {
          "activity" : "generate1",
          "start" : 247,
          "length" : 18
        },
        {
          "activity" : "generate2",
          "start" : 265,
          "length" : 146
        },
        {
          "activity" : "generateValidationPack",
          "start" : 284,
          "length" : 1
        }
      ]
    },
    {
      "name" : "fsh-generated/resources/ValueSet-WHO.TRUST.TRANSACTION.json",
      "size" : 484,
      "processes" : [
        {
          "activity" : "loadResources",
          "start" : 221,
          "length" : 3
        },
        {
          "activity" : "load",
          "start" : 221,
          "length" : 4
        },
        {
          "activity" : "generateNarratives",
          "start" : 222,
          "length" : 5
        },
        {
          "activity" : "validate",
          "start" : 223,
          "length" : 18
        },
        {
          "activity" : "generate1",
          "start" : 247,
          "length" : 13
        },
        {
          "activity" : "generate2",
          "start" : 266,
          "length" : 195
        },
        {
          "activity" : "generateExampleZip",
          "start" : 284,
          "length" : 1
        }
      ]
    }
  ]
}
